<?xml version="1.0" encoding="utf-8" standalone="yes"?>
<InfoWarnings>
  <Info>Begin full analysis with NDepend v2017.1.1</Info>
  <Info>Compare with analysis result obtained on 2017 April - 19 Wednesday 21:09  (which is the analysis result with date closest to 30 days ago)</Info>
  <Info>Concurrent mode</Info>
  <Info>.NET Assemblies loaded from {C:\Windows\Microsoft.NET\Framework\v4.0.30319} 
   mscorlib.dll   v4.0.0.0
   System.dll   v4.0.0.0</Info>
  <Warning>No application or third party assembly found in directory {C:\Windows\Microsoft.NET\Framework\v4.0.30319\WPF}</Warning>
  <Info>.NET Assembly loaded from {C:\Projects\Edgerunner FluentGuard\Org.Edgerunner.FluentGuard\bin\Debug} 
   Org.Edgerunner.FluentGuard.dll   v1.0.17121.1700</Info>
  <Warning>No application or third party assembly found in directory {C:\Projects\Edgerunner FluentGuard\Org.Edgerunner.FluentGuard\bin\Release}</Warning>
  <Warning>The source file {C:\Projects\Edgerunner FluentGuard\Org.Edgerunner.FluentGuard\Validation\NullableDateTimeValidator.cs} (last modified 5/2/2017 1:32:38 AM) and the PDB file of the assembly {Org.Edgerunner.FluentGuard} (last modified 5/2/2017 1:31:12 AM) are not in-sync.</Warning>
  <Info>18 source files parsed ; all source files found ; 1 source file not in-sync with PDB</Info>
  <Info>0 code rule has been extracted from code.</Info>
  <Info>No dependency cycle detected in assemblies referencement graph.</Info>
  <Info>Coverage file correctly parsed:
   \\Drobo\Projects\Edgerunner FluentGuard\All tests from Solution.xml</Info>
  <Info>Do merge code generated by compiler into application code.</Info>
  <Info>Analyse dependencies of your application.</Info>
  <Info>Log trend metrics values.</Info>
  <Info>Execute queries and rules.</Info>
  <Warning>5 quality gates fail.
  - 'Percentage Coverage on Refactored Code' value 55.56 % lower than fail threshold 70 %
  - 'New Blocker / Critical / Major Issues' value 85 issues greater than fail threshold 0 issues
  - 'Critical Rules Violated' value 1 rules greater than fail threshold 0 rules
  - 'Debt Rating per Namespace' value 1 namespaces greater than fail threshold 0 namespaces
  - 'New Annual Interest since Baseline' value 7.04 man-days greater than fail threshold 2 man-days</Warning>
  <Info>NDepend analysis done. Duration: 00:08</Info>
  <Info>Building the report (standard).</Info>
</InfoWarnings>